README
setup.cfg
setup.py
occult/__init__.py
occult/error.py
occult/main.py
occult.egg-info/PKG-INFO
occult.egg-info/SOURCES.txt
occult.egg-info/dependency_links.txt
occult.egg-info/entry_points.txt
occult.egg-info/namespace_packages.txt
occult.egg-info/not-zip-safe
occult.egg-info/requires.txt
occult.egg-info/top_level.txt
occult/json/__init__.py
occult/json/cli.py
occult/libraries/__init__.py
occult/libraries/minify_json.py
occult/libraries/mod_pbxproj.py
occult/libraries/mod_pbxproj3.py
occult/resource/__init__.py
occult/resource/cli.py
occult/template/__init__.py
occult/template/cli.py
occult/template/cmdreader.py
occult/template/configreader.py
occult/template/task.py
occult/template/taskmanager.py
occult/xcodeproj/__init__.py
occult/xcodeproj/cli.py