Metadata-Version: 1.1
Name: occult
Version: 0.1
Summary: Xcode Project Toolkit
Home-page: https://github.com/sodabiscuit/occult
Author: Yulin Ding
Author-email: sodabiscuit@gmail.com
License: UNKNOWN
Download-URL: https://github.com/sodabiscuit/occult/tarball/master
Platform: Any
Classifier: Development Status :: 2 - Pre-Alpha
Classifier: License :: OSI Approved :: MIT License
Classifier: Programming Language :: Python
Classifier: Programming Language :: Python :: 2
Classifier: Programming Language :: Python :: 2.7
Classifier: Intended Audience :: Developers
Classifier: Environment :: Console
